ehdtd_daemon/__init__.py
ehdtd_daemon/aux_common_functions.py
ehdtd_daemon/bin/ehdtd_daemon.py
ehdtd_daemon/etc/ehdtd-daemon/ehdtd-daemon-config-sample.yaml
ehdtd_daemon-0.2.25.dist-info/METADATA
ehdtd_daemon-0.2.25.dist-info/WHEEL
ehdtd_daemon-0.2.25.dist-info/entry_points.txt
ehdtd_daemon-0.2.25.dist-info/licenses/LICENSE
ehdtd_daemon-0.2.25.dist-info/RECORD
