Metadata-Version: 2.4
Name: ehdtd-daemon
Version: 0.2.25
Summary: Daemon script for ehdtd package
License: MIT
License-File: LICENSE
Author: Ricardo Marcelo Alvarez
Author-email: rmalvarezkai@gmail.com
Requires-Python: >=3.13,<4.0
Classifier: License :: OSI Approved :: MIT License
Classifier: Programming Language :: Python :: 3
Classifier: Programming Language :: Python :: 3.13
Classifier: Programming Language :: Python :: 3.14
Requires-Dist: ehdtd (>=0.2.36,<0.3.0)
Requires-Dist: importlib (>=1.0.4,<2.0.0)
Requires-Dist: logging (>=0.4.9.6,<0.5.0.0)
Requires-Dist: psycopg2-binary (>=2.9.11,<3.0.0)
Requires-Dist: pymysql (>=1.1.2,<2.0.0)
Requires-Dist: pyyaml (>=6.0.3,<7.0.0)
Project-URL: Homepage, https://github.com/rmalvarezkai/ehdtd_daemon
